CHANGELOG
MANIFEST.in
README.rst
setup.py
rerobots/__init__.py
rerobots/_version.py
rerobots/api.py
rerobots/cli.py
rerobots/instances.py
rerobots.egg-info/PKG-INFO
rerobots.egg-info/SOURCES.txt
rerobots.egg-info/dependency_links.txt
rerobots.egg-info/requires.txt
rerobots.egg-info/top_level.txt